terminal_manager/__init__.py
terminal_manager/collection.py
terminal_manager/command.py
terminal_manager/const.py
terminal_manager/error.py
terminal_manager/event.py
terminal_manager/helpers.py
terminal_manager/manager.py
terminal_manager/sensor.py
terminal_manager/state.py
terminal_manager/synchronizer.py
terminal_manager/terminal.py
terminal_manager/default_collections/__init__.py
terminal_manager/default_collections/linux.py
terminal_manager/default_collections/windows_cmd.py
terminal_manager/default_collections/windows_ps.py
terminal_manager-2.0.2.dist-info/licenses/LICENSE
terminal_manager-2.0.2.dist-info/METADATA
terminal_manager-2.0.2.dist-info/WHEEL
terminal_manager-2.0.2.dist-info/top_level.txt
terminal_manager-2.0.2.dist-info/RECORD
